audio_codec/__init__.py
audio_codec/mimi.py
audio_codec-0.0.2.dist-info/LICENSE
audio_codec-0.0.2.dist-info/METADATA
audio_codec-0.0.2.dist-info/WHEEL
audio_codec-0.0.2.dist-info/top_level.txt
audio_codec-0.0.2.dist-info/RECORD
